main.py
devflux_stock_mcp-0.0.0.dist-info/METADATA
devflux_stock_mcp-0.0.0.dist-info/WHEEL
devflux_stock_mcp-0.0.0.dist-info/entry_points.txt
devflux_stock_mcp-0.0.0.dist-info/top_level.txt
devflux_stock_mcp-0.0.0.dist-info/RECORD
