Metadata-Version: 2.4
Name: devflux-stock-mcp
Version: 0.0.0
Summary: stock mcp server
Author-email: mks <devplus.kr@gmail.com>
License-Expression: Apache-2.0
Project-URL: Homepage, https://mcp.devplus.co.kr/
Classifier: Development Status :: 4 - Beta
Classifier: Environment :: Console
Classifier: Intended Audience :: Developers
Classifier: Programming Language :: Python :: 3
Classifier: Programming Language :: Python :: 3.10
Classifier: Programming Language :: Python :: 3.11
Classifier: Programming Language :: Python :: 3.12
Classifier: Programming Language :: Python
Classifier: Topic :: Software Development
Requires-Python: >=3.12
